scriptloader.py
setup.py
scriptloader.egg-info/PKG-INFO
scriptloader.egg-info/SOURCES.txt
scriptloader.egg-info/dependency_links.txt
scriptloader.egg-info/entry_points.txt
scriptloader.egg-info/requires.txt
scriptloader.egg-info/top_level.txt