Metadata-Version: 1.0
Name: scriptloader
Version: 0.1.1
Summary: scriptloader loads scripts (into nose)
Home-page: http://packages.python.org/scriptloader
Author: Will Maier
Author-email: willmaier@ml1.net
License: UNKNOWN
Keywords: nose testing scripts
Platform: UNKNOWN
Classifier: Development Status :: 3 - Alpha
Classifier: Intended Audience :: Developers
Classifier: License :: OSI Approved :: BSD License
Classifier: License :: OSI Approved :: MIT License
Classifier: Natural Language :: English
Classifier: Programming Language :: Python
Classifier: Topic :: Software Development :: Testing
